nrdrch_ezdl/__init__.py
nrdrch_ezdl/__main__.py
nrdrch_ezdl/nrdrch_ezdl.py
nrdrch_ezdl/spot_url_resolver.py
nrdrch_ezdl/spotify_resolver.py
nrdrch_ezdl-1.2.1.dist-info/LICENSE
nrdrch_ezdl-1.2.1.dist-info/METADATA
nrdrch_ezdl-1.2.1.dist-info/WHEEL
nrdrch_ezdl-1.2.1.dist-info/entry_points.txt
nrdrch_ezdl-1.2.1.dist-info/top_level.txt
nrdrch_ezdl-1.2.1.dist-info/RECORD
