Metadata-Version: 2.1
Name: nrdrch-ezdl
Version: 1.2.1
Summary: yt-dlp wrapper for ultimate simplicity
Home-page: https://github.com/nrdrch/nrdrch-ezdl
Author: Lukas H
Author-email: nrdrch@proton.com
Project-URL: Bug Tracker, https://github.com/nrdrch/nrdrch-ezdl/issues
Classifier: Programming Language :: Python :: 3
Classifier: License :: OSI Approved :: MIT License
Classifier: Operating System :: Microsoft :: Windows :: Windows 10
Classifier: Operating System :: Microsoft :: Windows :: Windows 11
Requires-Python: >=3.9
License-File: LICENSE
Requires-Dist: rich >=13.7.1
Requires-Dist: toml >=0.10.2
Requires-Dist: yt-dlp >=2024.5.27
Requires-Dist: spotipy >=2.24.0
